{
  "parent": "minecraft:recipes/root",
  "criteria": {
    "has_lead_resin": {
      "conditions": {
        "items": [
          {
            "items": [
              "orechards:lead_resin"
            ]
          }
        ]
      },
      "trigger": "minecraft:inventory_changed"
    },
    "has_the_recipe": {
      "conditions": {
        "recipe": "minecraft:lead_amber"
      },
      "trigger": "minecraft:recipe_unlocked"
    }
  },
  "requirements": [
    [
      "has_lead_resin",
      "has_the_recipe"
    ]
  ],
  "rewards": {
    "recipes": [
      "minecraft:lead_amber"
    ]
  }
}