{
  "parent": "minecraft:recipes/root",
  "criteria": {
    "has_bacon_acorn": {
      "conditions": {
        "items": [
          {
            "items": [
              "orechards:bacon_acorn"
            ]
          }
        ]
      },
      "trigger": "minecraft:inventory_changed"
    },
    "has_the_recipe": {
      "conditions": {
        "recipe": "minecraft:bacon_acorn_roasted_from_furnace"
      },
      "trigger": "minecraft:recipe_unlocked"
    }
  },
  "requirements": [
    [
      "has_bacon_acorn",
      "has_the_recipe"
    ]
  ],
  "rewards": {
    "recipes": [
      "minecraft:bacon_acorn_roasted_from_furnace"
    ]
  }
}